{
"type": "FeatureCollection",
"name": "point4326json",
"crs": { "type": "name", "properties": { "name": "urn:ogc:def:crs:OGC:1.3:CRS84" } },
"features": [
{ "type": "Feature", "properties": { "id": 1 }, "geometry": { "type": "Point", "coordinates": [ -79.051236150544128, 35.912060629159484 ] } }
]
}
